LICENSE
README.rst
license.txt
setup.py
libTSCANAPI/TSCAN.py
libTSCANAPI/TSCommon.py
libTSCANAPI/TSDB.py
libTSCANAPI/TSDirver.py
libTSCANAPI/TSEnumdefine.py
libTSCANAPI/TSLDF.py
libTSCANAPI/TSMasterDevice.py
libTSCANAPI/TSPrase_Fibex.py
libTSCANAPI/TSStructure.py
libTSCANAPI/TSUDS.py
libTSCANAPI/__init__.py
libTSCANAPI/config.py
libTSCANAPI/dbc.py
libTSCANAPI/libtosun.py
libTSCANAPI.egg-info/PKG-INFO
libTSCANAPI.egg-info/SOURCES.txt
libTSCANAPI.egg-info/dependency_links.txt
libTSCANAPI.egg-info/requires.txt
libTSCANAPI.egg-info/top_level.txt
libTSCANAPI/linux/libLog.so
libTSCANAPI/linux/libTSCANApiOnLinux.so
libTSCANAPI/linux/libTSH.so
libTSCANAPI/linux/libbinlog.so
libTSCANAPI/rules/99-tosun.rules
libTSCANAPI/rules/说明.txt
libTSCANAPI/windows/x64/binlog.dll
libTSCANAPI/windows/x64/libLog.dll
libTSCANAPI/windows/x64/libTSCAN.dll
libTSCANAPI/windows/x64/libTSDevBase.dll
libTSCANAPI/windows/x64/libTSH.dll
libTSCANAPI/windows/x86/binlog.dll
libTSCANAPI/windows/x86/libLog.dll
libTSCANAPI/windows/x86/libTSCAN.dll
libTSCANAPI/windows/x86/libTSDevBase.dll
libTSCANAPI/windows/x86/libTSH.dll